quark_client/__init__.py
quark_client/client.py
quark_client/config.py
quark_client/exceptions.py
quark_client/auth/__init__.py
quark_client/auth/api_login.py
quark_client/auth/login.py
quark_client/auth/simple_login.py
quark_client/cli/__init__.py
quark_client/cli/__main__.py
quark_client/cli/interactive.py
quark_client/cli/main.py
quark_client/cli/utils.py
quark_client/cli/commands/__init__.py
quark_client/cli/commands/auth.py
quark_client/cli/commands/basic_fileops.py
quark_client/cli/commands/batch_share_commands.py
quark_client/cli/commands/download.py
quark_client/cli/commands/move_commands.py
quark_client/cli/commands/search.py
quark_client/cli/commands/share_commands.py
quark_client/core/__init__.py
quark_client/core/api_client.py
quark_client/services/__init__.py
quark_client/services/batch_share_service.py
quark_client/services/file_download_service.py
quark_client/services/file_service.py
quark_client/services/file_upload_service.py
quark_client/services/name_resolver.py
quark_client/services/share_service.py
quark_client/utils/__init__.py
quark_client/utils/logger.py
quark_client/utils/qr_code.py
quarkpan-1.0.5.dist-info/licenses/LICENSE
quarkpan-1.0.5.dist-info/METADATA
quarkpan-1.0.5.dist-info/WHEEL
quarkpan-1.0.5.dist-info/entry_points.txt
quarkpan-1.0.5.dist-info/top_level.txt
quarkpan-1.0.5.dist-info/RECORD
