Metadata-Version: 2.4
Name: quarkpan
Version: 1.0.5
Summary: 夸克网盘 Python 客户端和命令行工具
Author-email: QuarkPan Team <tequant.ai@gmail.com>
Maintainer-email: QuarkPan Team <tequant.ai@gmail.com>
License-Expression: MIT
Project-URL: Homepage, https://github.com/lich0821/QuarkPan
Project-URL: Bug Reports, https://github.com/lich0821/QuarkPan/issues
Project-URL: Source, https://github.com/lich0821/QuarkPan
Project-URL: Documentation, https://github.com/lich0821/QuarkPan/blob/main/docs/
Project-URL: Changelog, https://github.com/lich0821/QuarkPan/releases
Keywords: quark,pan,cloud,storage,cli,api,client,网盘
Classifier: Development Status :: 4 - Beta
Classifier: Intended Audience :: Developers
Classifier: Intended Audience :: End Users/Desktop
Classifier: Operating System :: OS Independent
Classifier: Programming Language :: Python :: 3
Classifier: Programming Language :: Python :: 3.8
Classifier: Programming Language :: Python :: 3.9
Classifier: Programming Language :: Python :: 3.10
Classifier: Programming Language :: Python :: 3.11
Classifier: Programming Language :: Python :: 3.12
Classifier: Topic :: Internet :: File Transfer Protocol (FTP)
Classifier: Topic :: System :: Archiving
Classifier: Topic :: Utilities
Classifier: Environment :: Console
Classifier: Natural Language :: Chinese (Simplified)
Requires-Python: >=3.8
License-File: LICENSE
Requires-Dist: httpx>=0.24.0
Requires-Dist: typer>=0.9.0
Requires-Dist: rich>=13.0.0
Requires-Dist: pydantic>=2.0.0
Requires-Dist: qrcode>=7.4.0
Requires-Dist: tqdm>=4.65.0
Provides-Extra: dev
Requires-Dist: pytest>=7.0.0; extra == "dev"
Requires-Dist: pytest-asyncio>=0.21.0; extra == "dev"
Requires-Dist: black; extra == "dev"
Requires-Dist: isort; extra == "dev"
Requires-Dist: flake8; extra == "dev"
Requires-Dist: mypy; extra == "dev"
Provides-Extra: test
Requires-Dist: pytest>=7.0.0; extra == "test"
Requires-Dist: pytest-asyncio>=0.21.0; extra == "test"
Requires-Dist: pytest-cov; extra == "test"
Dynamic: license-file
